AUTHORS.rst
CONTRIBUTING.rst
HISTORY.rst
LICENSE
MANIFEST.in
README.rst
setup.cfg
setup.py
brew/__init__.py
brew/base.py
brew.egg-info/PKG-INFO
brew.egg-info/SOURCES.txt
brew.egg-info/dependency_links.txt
brew.egg-info/not-zip-safe
brew.egg-info/requires.txt
brew.egg-info/top_level.txt
brew/combination/__init__.py
brew/combination/combiner.py
brew/combination/rules.py
brew/generation/__init__.py
brew/generation/bagging.py
brew/generation/base.py
brew/generation/ics_bagging.py
brew/generation/random_subspace.py
brew/generation/smote_bagging.py
brew/metrics/__init__.py
brew/metrics/evaluation.py
brew/metrics/diversity/__init__.py
brew/metrics/diversity/base.py
brew/metrics/diversity/non_paired.py
brew/metrics/diversity/paired.py
brew/preprocessing/__init__.py
brew/preprocessing/smote.py
brew/selection/__init__.py
brew/selection/dynamic/__init__.py
brew/selection/dynamic/base.py
brew/selection/dynamic/dsknn.py
brew/selection/dynamic/knora.py
brew/selection/dynamic/lca.py
brew/selection/dynamic/mcb.py
brew/selection/dynamic/ola.py
brew/selection/dynamic/probabilistic.py
brew/selection/pruning/__init__.py
brew/selection/pruning/base.py
brew/selection/pruning/epic.py
brew/selection/static/__init__.py
brew/stacking/__init__.py
brew/stacking/stacker.py
brew/utils/__init__.py
brew/utils/data.py
brew/utils/plot.py
test/test_brew.py
test/test_combination_rules.py
test/test_combiner.py
test/test_diversity_measures.py
test/test_ensemble.py
test/test_selection_dynamic.py