Metadata-Version: 1.1
Name: brew
Version: 0.1.4
Summary: BREW: Python Multiple Classifier System API
Home-page: https://github.com/viisar/brew
Author: Dayvid Victor <victor.dvro@gmail.com>, Thyago Porpino <thyago.porpino@gmail.com>
Author-email: brew-python-devs@googlegroups.com
License: MIT
Keywords: brew
Platform: UNKNOWN
Classifier: Programming Language :: Python
Classifier: Programming Language :: Python :: 3
Classifier: License :: OSI Approved :: MIT License
Classifier: Development Status :: 2 - Pre-Alpha
Classifier: Intended Audience :: Science/Research
Classifier: Intended Audience :: Developers
Classifier: Natural Language :: English
Classifier: Topic :: Scientific/Engineering
